leaguecloser/__init__.py
leaguecloser/computer.py
leaguecloser/league.py
leaguecloser/sikuli.py
leaguecloser/data/close_league.sikuli/1681351869136.png
leaguecloser/data/close_league.sikuli/1681352088077.png
leaguecloser/data/close_league.sikuli/close_league.py
leaguecloser-1.0.5.dist-info/LICENSE
leaguecloser-1.0.5.dist-info/METADATA
leaguecloser-1.0.5.dist-info/WHEEL
leaguecloser-1.0.5.dist-info/top_level.txt
leaguecloser-1.0.5.dist-info/RECORD
