Metadata-Version: 2.1
Name: leaguecloser
Version: 1.0.5
Summary: Mock package that auto-closes the League client
Author: Giantpizzahead
Project-URL: Homepage, https://github.com/Giantpizzahead/auto-league-closer
Classifier: Programming Language :: Python :: 3
Classifier: License :: OSI Approved :: MIT License
Classifier: Operating System :: Microsoft :: Windows
License-File: LICENSE
Requires-Dist: psutil
Requires-Dist: pyautogui
Requires-Dist: pywin32
Requires-Dist: requests
